{
  "id": "E4-S3",
  "type": "story",
  "status": "merged",
  "title": "S3: Full Validate (W1-W11 + E1-E12)",
  "parent": "E4",
  "children": [
    "E4-S3-T1",
    "E4-S3-T2"
  ],
  "blocked_by": [
    "E4-S2"
  ],
  "blocks": [
    "E4-S5"
  ],
  "definition_of_done": "All W1-W11 warning checks and E1-E12 error checks implemented, --scope/--strict/JSON output flags on validate command; all tests pass",
  "scope": null,
  "provenance": {
    "method": "decomposed",
    "confidence": "verified",
    "source_worker": "0fb9a1c9-195f-4c03-84e2-487ad18c69e7"
  },
  "decision_refs": [],
  "outcome": "Full validation suite complete: W1-W11 warnings, E2-E12 errors, --scope/--strict/--ci flags, JSON output",
  "source_links": [
    {
      "source_entry_id": "253e1536-283c-4c2b-9cf5-26fba5496076",
      "source_url": "docs/superpowers/plans/2026-03-18-e4-s3-full-validate.md"
    }
  ],
  "updated": 1774468195
}