{
  "id": "E5-S0-T1",
  "type": "task",
  "status": "merged",
  "title": "Confidence field in materialized state and draft gate in ready queue",
  "parent": "E5-S0",
  "children": [],
  "blocked_by": [],
  "blocks": [
    "E5-S0-T2"
  ],
  "priority": "high",
  "definition_of_done": "draft nodes excluded from trls ready; verified nodes appear normally; existing nodes without confidence field default to verified; tests pass; make check green",
  "scope": [
    "internal/ops/types.go, internal/materialize/materialize.go, internal/ready/compute.go, cmd/trellis/main_test.go"
  ],
  "provenance": {
    "method": "decomposed",
    "confidence": "verified",
    "source_worker": "95cf736f-4bc5-4c02-82da-37e5192fb429"
  },
  "decision_refs": [],
  "outcome": "Added confidence field to op Payload and materialized Issue; draft gate in ComputeReady excludes draft nodes; existing nodes without confidence default to verified; --confidence flag on trls create; 9 new tests (unit + integration); make check green",
  "claimed_by": "c69e037b-ef1d-4875-a05f-f5f0bd436682",
  "claimed_at": 1774231538,
  "claim_ttl": 60,
  "last_heartbeat": 1774231538,
  "updated": 1774232136
}