{
  "E2-001": {
    "status": "merged",
    "type": "story",
    "children": [
      "E2-001-T1",
      "E2-001-T2",
      "E2-001-T3",
      "E2-001-T4",
      "E2-001-T5",
      "E2-001-T6"
    ],
    "blocks": [
      "E2-002",
      "E2-003",
      "E2-004"
    ],
    "updated": 1773622697,
    "title": "Implement multi-branch mode",
    "outcome": "Multi-branch mode fully implemented: issues dir path resolution abstracted by config mode, orphan branch/worktree management, all op reads/writes routed through AppendAndCommit for branch isolation, materialize pipeline mode-aware, init supports --dual-branch flag, SingleBranchMode derived from config. AgentSkill for trls also shipped."
  },
  "E2-001-T1": {
    "status": "merged",
    "type": "task",
    "parent": "E2-001",
    "blocks": [
      "E2-001-T3",
      "E2-001-T4"
    ],
    "assignee": "936c1188-4116-403f-a5ca-5ed7d9c6bf2b",
    "updated": 1773617356,
    "title": "Abstract issues directory path resolution by config mode"
  },
  "E2-001-T2": {
    "status": "merged",
    "type": "task",
    "parent": "E2-001",
    "blocks": [
      "E2-001-T5"
    ],
    "assignee": "936c1188-4116-403f-a5ca-5ed7d9c6bf2b",
    "updated": 1773622669,
    "title": "Git worktree management for issues branch",
    "outcome": "Added orphan branch, worktree, and git config helpers in internal/git. Init command gained --dual-branch flag that creates _trellis orphan branch and .trellis worktree."
  },
  "E2-001-T3": {
    "status": "merged",
    "type": "task",
    "parent": "E2-001",
    "blocked_by": [
      "E2-001-T1"
    ],
    "assignee": "9ac4202c-8256-4f5e-8e21-9b5de7840ddb",
    "updated": 1773622679,
    "title": "Route op reads/writes through abstracted path",
    "outcome": "All worker op writes now route through AppendAndCommit which handles branch isolation. CommitWorktreeOp added in git adapter. Integration test added for dual-branch op isolation."
  },
  "E2-001-T4": {
    "status": "merged",
    "type": "task",
    "parent": "E2-001",
    "blocked_by": [
      "E2-001-T1"
    ],
    "blocks": [
      "E2-001-T6"
    ],
    "assignee": "9ac4202c-8256-4f5e-8e21-9b5de7840ddb",
    "updated": 1773622679,
    "title": "Materialize pipeline accepts dynamic issues dir",
    "outcome": "Materialize engine SingleBranchMode now derived from appCtx.Mode instead of hardcoded true. WorktreePath added to Context. Pipeline reads ops from correct location based on mode."
  },
  "E2-001-T5": {
    "status": "merged",
    "type": "task",
    "parent": "E2-001",
    "blocked_by": [
      "E2-001-T2"
    ],
    "assignee": "9ac4202c-8256-4f5e-8e21-9b5de7840ddb",
    "updated": 1773622687,
    "title": "Init command supports dual-branch mode flag",
    "outcome": "trls init --dual-branch creates orphan issues branch, sets up .trellis worktree, and writes config with Mode=dual-branch. Implemented in cmd/trellis/main.go."
  },
  "E2-001-T6": {
    "status": "merged",
    "type": "task",
    "parent": "E2-001",
    "blocked_by": [
      "E2-001-T4"
    ],
    "assignee": "9ac4202c-8256-4f5e-8e21-9b5de7840ddb",
    "updated": 1773622687,
    "title": "SingleBranchMode flag derived from config",
    "outcome": "Materialize engine SingleBranchMode flag derived from appCtx.Mode via feat(mode) commit. In dual-branch mode, done does not auto-promote to merged."
  },
  "E2-002": {
    "status": "merged",
    "type": "story",
    "blocked_by": [
      "E2-001"
    ],
    "assignee": "0ee1fde3-66ea-4a21-be2b-872e22c61109",
    "updated": 1773623097,
    "title": "Branch isolation for worker operations",
    "outcome": "Branch isolation for worker operations complete. All worker op writes (claim, note, heartbeat, transition, create, link, decision, reopen, merged) route through appendOp/AppendAndCommit. In dual-branch mode, each op is committed to the _trellis branch worktree. Fixed remaining ops.AppendOp call in claim.go scope-overlap path. All tests pass."
  },
  "E2-003": {
    "status": "merged",
    "type": "story",
    "blocked_by": [
      "E2-001"
    ],
    "assignee": "c2d36434-9b2a-4303-a2ea-f140cbb1db80",
    "updated": 1773624455,
    "title": "Cross-branch merge detection and auto-transition",
    "outcome": "Implemented trls sync command with BranchMergedInto git detection, internal/sync DetectMerges logic, cmd/trellis/sync.go command, and post-merge.sh.template hook. All tests pass."
  },
  "E2-004": {
    "status": "merged",
    "type": "story",
    "blocked_by": [
      "E2-001"
    ],
    "updated": 1773625149,
    "title": "PR-based done-to-merged workflow",
    "outcome": "PR-based done-to-merged workflow: IndexEntry Branch/PR fields, trls status awaiting-merge callout, trls merged done-state validation and --pr flag, full e2e test. All tests pass."
  },
  "E3": {
    "status": "open",
    "type": "story",
    "children": [
      "E3-001",
      "E3-003",
      "E3-004",
      "E3-002",
      "E3-T13"
    ],
    "updated": 1773668289,
    "title": "E3: Multi-Worker Collaboration",
    "scope": [
      "internal/**"
    ]
  },
  "E3-001": {
    "status": "open",
    "type": "story",
    "parent": "E3",
    "children": [
      "E3-001-T1",
      "E3-001-T2",
      "E3-001-T3",
      "E3-001-T4",
      "E3-001-T5"
    ],
    "blocks": [
      "E3-004"
    ],
    "updated": 1773668289,
    "title": "Push/Sync Layer — remote sync for _trellis branch",
    "scope": [
      "internal/git/**"
    ]
  },
  "E3-001-T1": {
    "status": "open",
    "type": "task",
    "parent": "E3-001",
    "blocks": [
      "E3-001-T2"
    ],
    "updated": 1773668289,
    "title": "Add LowStakesPushThreshold to Config",
    "scope": [
      "internal/config/**"
    ]
  },
  "E3-001-T2": {
    "status": "open",
    "type": "task",
    "parent": "E3-001",
    "blocked_by": [
      "E3-001-T1"
    ],
    "blocks": [
      "E3-001-T3"
    ],
    "updated": 1773668289,
    "title": "Add Push and FetchAndRebase to git.Client",
    "scope": [
      "internal/git/**"
    ]
  },
  "E3-001-T3": {
    "status": "open",
    "type": "task",
    "parent": "E3-001",
    "blocked_by": [
      "E3-001-T2"
    ],
    "blocks": [
      "E3-001-T4"
    ],
    "updated": 1773668289,
    "title": "Pusher interface + NoPusher + AppendCommitAndPush",
    "scope": [
      "internal/ops/**"
    ]
  },
  "E3-001-T4": {
    "status": "open",
    "type": "task",
    "parent": "E3-001",
    "blocked_by": [
      "E3-001-T3"
    ],
    "blocks": [
      "E3-001-T5"
    ],
    "updated": 1773668289,
    "title": "PendingPushTracker + FilePushTracker + NoTracker",
    "scope": [
      "internal/ops/**"
    ]
  },
  "E3-001-T5": {
    "status": "open",
    "type": "task",
    "parent": "E3-001",
    "blocked_by": [
      "E3-001-T4"
    ],
    "blocks": [
      "E3-T13"
    ],
    "updated": 1773668289,
    "title": "Wire push deps through command helpers",
    "scope": [
      "cmd/trellis/**"
    ]
  },
  "E3-002": {
    "status": "open",
    "type": "story",
    "parent": "E3",
    "children": [
      "E3-002-T12"
    ],
    "blocked_by": [
      "E3-004-T9"
    ],
    "updated": 1773668289,
    "title": "Worker Presence — trls workers command",
    "scope": [
      "cmd/trellis/**"
    ]
  },
  "E3-002-T12": {
    "status": "open",
    "type": "task",
    "parent": "E3-002",
    "blocked_by": [
      "E3-004-T9"
    ],
    "blocks": [
      "E3-T13"
    ],
    "updated": 1773668289,
    "title": "trls workers command",
    "scope": [
      "cmd/trellis/**"
    ]
  },
  "E3-003": {
    "status": "open",
    "type": "story",
    "parent": "E3",
    "children": [
      "E3-003-T6",
      "E3-003-T7"
    ],
    "updated": 1773668289,
    "title": "Audit Log Viewer — trls log command",
    "scope": [
      "internal/audit/**"
    ]
  },
  "E3-003-T6": {
    "status": "open",
    "type": "task",
    "parent": "E3-003",
    "blocks": [
      "E3-003-T7"
    ],
    "updated": 1773668289,
    "title": "internal/audit/audit.go",
    "scope": [
      "internal/audit/**"
    ]
  },
  "E3-003-T7": {
    "status": "open",
    "type": "task",
    "parent": "E3-003",
    "blocked_by": [
      "E3-003-T6"
    ],
    "blocks": [
      "E3-T13"
    ],
    "updated": 1773668289,
    "title": "trls log command",
    "scope": [
      "cmd/trellis/**"
    ]
  },
  "E3-004": {
    "status": "open",
    "type": "story",
    "parent": "E3",
    "children": [
      "E3-004-T8",
      "E3-004-T9",
      "E3-004-T10",
      "E3-004-T11"
    ],
    "blocked_by": [
      "E3-001"
    ],
    "updated": 1773668289,
    "title": "Issue Assignment — trls assign/unassign + ready sort",
    "scope": [
      "internal/ops/**"
    ]
  },
  "E3-004-T10": {
    "status": "open",
    "type": "task",
    "parent": "E3-004",
    "blocked_by": [
      "E3-004-T9"
    ],
    "blocks": [
      "E3-T13"
    ],
    "updated": 1773668289,
    "title": "trls assign and trls unassign commands",
    "scope": [
      "cmd/trellis/**"
    ]
  },
  "E3-004-T11": {
    "status": "open",
    "type": "task",
    "parent": "E3-004",
    "blocked_by": [
      "E3-004-T9"
    ],
    "blocks": [
      "E3-T13"
    ],
    "updated": 1773668289,
    "title": "Assignment-aware ready sort in ComputeReady",
    "scope": [
      "internal/ready/**"
    ]
  },
  "E3-004-T8": {
    "status": "open",
    "type": "task",
    "parent": "E3-004",
    "blocks": [
      "E3-004-T9"
    ],
    "updated": 1773668289,
    "title": "OpAssign type registration + schema + log.go OpAssign case",
    "scope": [
      "internal/ops/**"
    ]
  },
  "E3-004-T9": {
    "status": "open",
    "type": "task",
    "parent": "E3-004",
    "blocked_by": [
      "E3-004-T8"
    ],
    "blocks": [
      "E3-004-T10",
      "E3-004-T11",
      "E3-002",
      "E3-002-T12"
    ],
    "updated": 1773668289,
    "title": "Materialization: AssignedWorker field + applyAssign handler",
    "scope": [
      "internal/materialize/**"
    ]
  },
  "E3-T13": {
    "status": "open",
    "type": "task",
    "parent": "E3",
    "blocked_by": [
      "E3-001-T5",
      "E3-003-T7",
      "E3-004-T10",
      "E3-004-T11",
      "E3-002-T12"
    ],
    "updated": 1773668289,
    "title": "Final Integration — build, test, all commands registered",
    "scope": [
      "cmd/trellis/**"
    ]
  }
}